auxi/core/__init__.py
auxi/core/py.typed
auxi/core/bibliography/__init__.py
auxi/core/bibliography/_library.py
auxi/core/bibliography/py.typed
auxi/core/data/bibliography.bib
auxi/core/matter/__init__.py
auxi/core/matter/_state_of_matter.py
auxi/core/matter/py.typed
auxi/core/objects/__init__.py
auxi/core/objects/_named_object.py
auxi/core/objects/_object.py
auxi/core/objects/py.typed
auxi/core/physicalconstants/__init__.py
auxi/core/physicalconstants/_constants.py
auxi/core/physicalconstants/py.typed
auxi/core/reporting/__init__.py
auxi/core/reporting/_report.py
auxi/core/reporting/_report_format.py
auxi/core/reporting/py.typed
auxi/core/time/__init__.py
auxi/core/time/_clock.py
auxi/core/time/_time_period.py
auxi/core/time/py.typed
auxi/core/validation/__init__.py
auxi/core/validation/_floats.py
auxi/core/validation/_ints.py
auxi/core/validation/_strings.py
auxi/core/validation/py.typed
auxi_core-2.2.4.dist-info/licenses/LICENSE.md
auxi_core-2.2.4.dist-info/METADATA
auxi_core-2.2.4.dist-info/WHEEL
auxi_core-2.2.4.dist-info/top_level.txt
auxi_core-2.2.4.dist-info/RECORD
