Metadata-Version: 2.4
Name: auxi-core
Version: 2.2.4
Summary: `auxi` provides tools to help users do calculations for metallurgical process engineering. `auxi-core` provides base infrastructure used by other `auxi` packages.
Author-email: Johan Zietsman <johan.zietsman@ex-mente.co.za>
Maintainer-email: Stefan van der Merwe <stefan.vandermerwe@ex-mente.co.za>, Thys Nortje <thys.nortje@ex-mente.co.za>
License: # MIT License
Classifier: Development Status :: 5 - Production/Stable
Classifier: Programming Language :: Python :: 3
Classifier: Operating System :: POSIX :: Linux
Classifier: Environment :: Console
Requires-Python: >=3.12
License-File: LICENSE.md
Requires-Dist: bibtexparser>=2.0.0b7
Requires-Dist: pydantic>=2.9.2
Requires-Dist: python-dateutil>=2.9.0.post0
Requires-Dist: tabulate>=0.9.0
Dynamic: license-file
